fpga/rtl/book/book2.v
`timescale 1ns / 1ps

module book2 (
    input wire clk,
    input wire rst,
    
    // Input from Decoder
    input wire tick_valid,
    input wire tick_type, // 0 = Add, 1 = Exec
    input wire tick_side, // 1 = Buy, 0 = Sell
    input wire [31:0] tick_qty,
    input wire [31:0] tick_price,
    
    // L1 Output (Best Bid / Best Offer)
    output reg [31:0] bid_px0,
    output reg [31:0] bid_sz0,
    output reg [31:0] ask_px0,
    output reg [31:0] ask_sz0
);

    localparam INVALID_PX_ASK = 32'hFFFFFFFF;
    localparam INVALID_PX_BID = 32'h00000000;

    always @(posedge clk) begin
        if (rst) begin
            bid_px0 <= INVALID_PX_BID;
            bid_sz0 <= 0;
            ask_px0 <= INVALID_PX_ASK;
            ask_sz0 <= 0;
        end else begin
            if (tick_valid) begin
                if (tick_type == 1'b0) begin // ADD ORDER
                    if (tick_side == 1'b1) begin // BUY
                        if (tick_price > bid_px0 || bid_px0 == INVALID_PX_BID) begin
                            bid_px0 <= tick_price;
                            bid_sz0 <= tick_qty;
                        end else if (tick_price == bid_px0) begin
                            bid_sz0 <= bid_sz0 + tick_qty;
                        end
                    end else begin // SELL
                        if (tick_price < ask_px0 || ask_px0 == INVALID_PX_ASK) begin
                            ask_px0 <= tick_price;
                            ask_sz0 <= tick_qty;
                        end else if (tick_price == ask_px0) begin
                            ask_sz0 <= ask_sz0 + tick_qty;
                        end
                    end
                end
                // Simplified: Not handling Executions/Cancels in this L1 baseline snippet
                // as it requires a full order-ID map memory (TCAM/RAM) which is Phase 4.
            end
        end
    end

endmodule

apps/fpga-sim/work/tb_book2_injected.v
`timescale 1ns / 1ps

module tb_book2;

    reg clk;
    reg rst;
    reg tick_valid;
    reg tick_type;
    reg tick_side;
    reg [31:0] tick_qty;
    reg [31:0] tick_price;

    wire [31:0] bid_px0;
    wire [31:0] bid_sz0;
    wire [31:0] ask_px0;
    wire [31:0] ask_sz0;

    book2 uut (
        .clk(clk), .rst(rst),
        .tick_valid(tick_valid), .tick_type(tick_type),
        .tick_side(tick_side), .tick_qty(tick_qty), .tick_price(tick_price),
        .bid_px0(bid_px0), .bid_sz0(bid_sz0), .ask_px0(ask_px0), .ask_sz0(ask_sz0)
    );

    initial begin
        clk = 0;
        forever #5 clk = ~clk;
    end

    initial begin
        rst = 1;
        tick_valid = 0;
        tick_type = 0;
        tick_side = 0;
        tick_qty = 0;
        tick_price = 0;
        
        #100;
        rst = 0;
        #20;

        // 1. Add a BID at 100.00 (10000 units)
        @(posedge clk);
        tick_valid = 1; tick_type = 0; tick_side = 1; tick_qty = 10; tick_price = 10000;
        @(posedge clk);
        tick_valid = 0;
        
        // 2. Add an ASK at 100.10 (10010 units)
        @(posedge clk);
        tick_valid = 1; tick_type = 0; tick_side = 0; tick_qty = 5; tick_price = 10010;
        @(posedge clk);
        tick_valid = 0;

        // 3. Add a better BID at 100.05
        @(posedge clk);
        tick_valid = 1; tick_type = 0; tick_side = 1; tick_qty = 20; tick_price = 10005;
        @(posedge clk);
        tick_valid = 0;

        #50;
        if (bid_px0 == 10005 && ask_px0 == 10010)
            $display("PASS: Order Book BBO Correctly Updated");
        else
            $display("FAIL: Order Book Mismatch. Bid: %d, Ask: %d", bid_px0, ask_px0);

        $finish;
    end

    initial begin
        $dumpfile("/Users/shreejitverma/Documents/GitHub/ultra-hft-project/apps/fpga-sim/waveforms/tb_book2.vcd");
        $dumpvars(0, tb_book2);
    end
endmodule

apps/fpga-sim/waveforms/tb_book2.vcd
$date
	Wed Feb 25 20:07:30 2026
$end
$version
	Icarus Verilog
$end
$timescale
	1ps
$end
$scope module tb_book2 $end
$var wire 32 ! bid_sz0 [31:0] $end
$var wire 32 " bid_px0 [31:0] $end
$var wire 32 # ask_sz0 [31:0] $end
$var wire 32 $ ask_px0 [31:0] $end
$var reg 1 % clk $end
$var reg 1 & rst $end
$var reg 32 ' tick_price [31:0] $end
$var reg 32 ( tick_qty [31:0] $end
$var reg 1 ) tick_side $end
$var reg 1 * tick_type $end
$var reg 1 + tick_valid $end
$scope module uut $end
$var wire 1 % clk $end
$var wire 1 & rst $end
$var wire 32 , tick_price [31:0] $end
$var wire 32 - tick_qty [31:0] $end
$var wire 1 ) tick_side $end
$var wire 1 * tick_type $end
$var wire 1 + tick_valid $end
$var parameter 32 . INVALID_PX_ASK $end
$var parameter 32 / INVALID_PX_BID $end
$var reg 32 0 ask_px0 [31:0] $end
$var reg 32 1 ask_sz0 [31:0] $end
$var reg 32 2 bid_px0 [31:0] $end
$var reg 32 3 bid_sz0 [31:0] $end
$upscope $end
$upscope $end
$enddefinitions $end
$comment Show the parameter values. $end
$dumpall
b0 /
b11111111111111111111111111111111 .
$end
#0
$dumpvars
bx 3
bx 2
bx 1
bx 0
b0 -
b0 ,
0+
0*
0)
b0 (
b0 '
1&
0%
bx $
bx #
bx "
bx !
$end
#5000
b0 #
b0 1
b11111111111111111111111111111111 $
b11111111111111111111111111111111 0
b0 !
b0 3
b0 "
b0 2
1%
#10000
0%
#15000
1%
#20000
0%
#25000
1%
#30000
0%
#35000
1%
#40000
0%
#45000
1%
#50000
0%
#55000
1%
#60000
0%
#65000
1%
#70000
0%
#75000
1%
#80000
0%
#85000
1%
#90000
0%
#95000
1%
#100000
0%
0&
#105000
1%
#110000
0%
#115000
1%
#120000
0%
#125000
b1010 !
b1010 3
b10011100010000 "
b10011100010000 2
b10011100010000 '
b10011100010000 ,
b1010 (
b1010 -
1)
1+
1%
#130000
0%
#135000
b10100 !
b10100 3
0+
1%
#140000
0%
#145000
b101 #
b101 1
b10011100011010 $
b10011100011010 0
b10011100011010 '
b10011100011010 ,
b101 (
b101 -
0)
1+
1%
#150000
0%
#155000
b1010 #
b1010 1
0+
1%
#160000
0%
#165000
b10011100010101 "
b10011100010101 2
b10011100010101 '
b10011100010101 ,
b10100 (
b10100 -
1)
1+
1%
#170000
0%
#175000
b101000 !
b101000 3
0+
1%
