fpga/rtl/parsers/rx_parser.v
`timescale 1ns / 1ps

module rx_parser #(
    parameter DATA_W = 64
) (
    input wire clk,
    input wire rst,
    
    // AXI-Stream Slave (Input from PHY/MAC)
    input wire [DATA_W-1:0] s_axis_tdata,
    input wire s_axis_tvalid,
    input wire s_axis_tlast,
    output wire s_axis_tready,
    
    // AXI-Stream Master (Output Payload)
    output reg [DATA_W-1:0] m_axis_tdata,
    output reg m_axis_tvalid,
    output reg m_axis_tlast,
    input wire m_axis_tready,
    
    // Extracted Header Fields
    output reg [31:0] ip_src,
    output reg [31:0] ip_dst,
    output reg [15:0] udp_sport,
    output reg [15:0] udp_dport,
    output reg header_valid
);

    // Flow control: We are ready if downstream is ready
    assign s_axis_tready = m_axis_tready;

    // State Machine
    localparam ST_ETH = 2'd0;
    localparam ST_IP  = 2'd1;
    localparam ST_UDP = 2'd2;
    localparam ST_PAY = 2'd3;

    reg [1:0] state;

    always @(posedge clk) begin
        if (rst) begin
            state <= ST_ETH;
            m_axis_tvalid <= 1'b0;
            m_axis_tlast <= 1'b0;
            header_valid <= 1'b0;
        end else begin
            // Default assignments
            m_axis_tvalid <= 1'b0;
            m_axis_tlast <= 1'b0;
            
            if (s_axis_tlast) header_valid <= 1'b0; 

            if (s_axis_tvalid && s_axis_tready) begin
                case(state)
                    ST_ETH: begin
                        // Cycle 0: DstMAC[47:0] + SrcMAC[15:0] -> Not extracting here for sim
                        state <= ST_IP; 
                    end
                    
                    ST_IP: begin
                        // Extraction (Simplified logic for thesis demonstration)
                        // Assumes IP Src/Dst are aligned in this cycle
                        ip_src <= s_axis_tdata[31:0];
                        ip_dst <= s_axis_tdata[63:32];
                        state <= ST_UDP;
                    end
                    
                    ST_UDP: begin
                        // Extraction
                        udp_sport <= s_axis_tdata[15:0];
                        udp_dport <= s_axis_tdata[31:16];
                        header_valid <= 1'b1;
                        state <= ST_PAY;
                    end
                    
                    ST_PAY: begin
                        m_axis_tdata <= s_axis_tdata;
                        m_axis_tvalid <= 1'b1;
                        m_axis_tlast <= s_axis_tlast;
                        
                        if (s_axis_tlast) begin
                            state <= ST_ETH;
                            header_valid <= 1'b0;
                        end
                    end
                endcase
            end
        end
    end

endmodule

apps/fpga-sim/work/tb_rx_parser_injected.v
`timescale 1ns / 1ps

module tb_rx_parser;

    // Parameters
    parameter DATA_W = 64;
    
    // Inputs
    reg clk;
    reg rst;
    reg [DATA_W-1:0] s_axis_tdata;
    reg s_axis_tvalid;
    reg s_axis_tlast;
    reg m_axis_tready;

    // Outputs
    wire s_axis_tready;
    wire [DATA_W-1:0] m_axis_tdata;
    wire m_axis_tvalid;
    wire m_axis_tlast;
    wire [31:0] ip_src;
    wire [31:0] ip_dst;
    wire [15:0] udp_sport;
    wire [15:0] udp_dport;
    wire header_valid;

    // Instantiate the Unit Under Test (UUT)
    rx_parser #(
        .DATA_W(DATA_W)
    ) uut (
        .clk(clk), 
        .rst(rst), 
        .s_axis_tdata(s_axis_tdata), 
        .s_axis_tvalid(s_axis_tvalid), 
        .s_axis_tlast(s_axis_tlast), 
        .s_axis_tready(s_axis_tready), 
        .m_axis_tdata(m_axis_tdata), 
        .m_axis_tvalid(m_axis_tvalid), 
        .m_axis_tlast(m_axis_tlast), 
        .m_axis_tready(m_axis_tready), 
        .ip_src(ip_src), 
        .ip_dst(ip_dst), 
        .udp_sport(udp_sport), 
        .udp_dport(udp_dport), 
        .header_valid(header_valid)
    );

    // Clock generation
    initial begin
        clk = 0;
        forever #5 clk = ~clk; // 100MHz
    end

    // Test Sequence
    initial begin
        // Initialize Inputs
        rst = 1;
        s_axis_tdata = 0;
        s_axis_tvalid = 0;
        s_axis_tlast = 0;
        m_axis_tready = 1; // Always ready to receive payload

        // Wait 100 ns for global reset to finish
        #100;
        rst = 0;
        #20;

        // --- Send Packet ---
        // Cycle 1: Ethernet Header (DstMAC + SrcMAC partial) -> Logic assumes skip
        @(posedge clk);
        s_axis_tvalid = 1;
        s_axis_tdata = 64'hAA_BB_CC_DD_EE_FF_11_22; // Garbage MACs
        
        // Cycle 2: IP Header starts (Logic expects IP Src/Dst here)
        // SrcIP: 192.168.1.1 (C0 A8 01 01)
        // DstIP: 224.1.1.1 (E0 01 01 01) (Multicast)
        @(posedge clk);
        s_axis_tdata = 64'hC0A80101_E0010101; 
        
        // Cycle 3: UDP Header (Sport, Dport)
        // Sport: 1234 (04D2)
        // Dport: 8080 (1F90)
        // Len/Chksum garbage
        @(posedge clk);
        s_axis_tdata = 64'h04D2_1F90_0000_0000;
        
        // Cycle 4: Payload Word 1
        @(posedge clk);
        s_axis_tdata = 64'hDEAD_BEEF_CAFE_BABE;
        
        // Cycle 5: Payload Word 2 (Last)
        @(posedge clk);
        s_axis_tdata = 64'h1111_2222_3333_4444;
        s_axis_tlast = 1;
        
        @(posedge clk);
        s_axis_tvalid = 0;
        s_axis_tlast = 0;

        // Wait and Check
        #50;
        
        // Check results (Self-Checking)
        if (ip_src == 32'hC0A80101 && ip_dst == 32'hE0010101) 
            $display("PASS: IP Addresses Parsed Correctly");
        else 
            $display("FAIL: IP Address Mismatch. Src: %h, Dst: %h", ip_src, ip_dst);
            
        if (udp_dport == 16'h1F90)
            $display("PASS: UDP Port Parsed Correctly");
        else
            $display("FAIL: UDP Port Mismatch: %h", udp_dport);

        $finish;
    end
      
    initial begin
        $dumpfile("/Users/shreejitverma/Documents/GitHub/ultra-hft-project/apps/fpga-sim/waveforms/tb_rx_parser.vcd");
        $dumpvars(0, tb_rx_parser);
    end
endmodule

apps/fpga-sim/waveforms/tb_rx_parser.vcd
$date
	Wed Feb 25 20:07:30 2026
$end
$version
	Icarus Verilog
$end
$timescale
	1ps
$end
$scope module tb_rx_parser $end
$var wire 16 ! udp_sport [15:0] $end
$var wire 16 " udp_dport [15:0] $end
$var wire 1 # s_axis_tready $end
$var wire 1 $ m_axis_tvalid $end
$var wire 1 % m_axis_tlast $end
$var wire 64 & m_axis_tdata [63:0] $end
$var wire 32 ' ip_src [31:0] $end
$var wire 32 ( ip_dst [31:0] $end
$var wire 1 ) header_valid $end
$var parameter 32 * DATA_W $end
$var reg 1 + clk $end
$var reg 1 , m_axis_tready $end
$var reg 1 - rst $end
$var reg 64 . s_axis_tdata [63:0] $end
$var reg 1 / s_axis_tlast $end
$var reg 1 0 s_axis_tvalid $end
$scope module uut $end
$var wire 1 + clk $end
$var wire 1 , m_axis_tready $end
$var wire 1 - rst $end
$var wire 64 1 s_axis_tdata [63:0] $end
$var wire 1 / s_axis_tlast $end
$var wire 1 # s_axis_tready $end
$var wire 1 0 s_axis_tvalid $end
$var parameter 32 2 DATA_W $end
$var parameter 2 3 ST_ETH $end
$var parameter 2 4 ST_IP $end
$var parameter 2 5 ST_PAY $end
$var parameter 2 6 ST_UDP $end
$var reg 1 ) header_valid $end
$var reg 32 7 ip_dst [31:0] $end
$var reg 32 8 ip_src [31:0] $end
$var reg 64 9 m_axis_tdata [63:0] $end
$var reg 1 % m_axis_tlast $end
$var reg 1 $ m_axis_tvalid $end
$var reg 2 : state [1:0] $end
$var reg 16 ; udp_dport [15:0] $end
$var reg 16 < udp_sport [15:0] $end
$upscope $end
$upscope $end
$enddefinitions $end
$comment Show the parameter values. $end
$dumpall
b10 6
b11 5
b1 4
b0 3
b1000000 2
b1000000 *
$end
#0
$dumpvars
bx <
bx ;
bx :
bx 9
bx 8
bx 7
b0 1
00
0/
b0 .
1-
1,
0+
x)
bx (
bx '
bx &
x%
x$
1#
bx "
bx !
$end
#5000
0)
0%
0$
b0 :
1+
#10000
0+
#15000
1+
#20000
0+
#25000
1+
#30000
0+
#35000
1+
#40000
0+
#45000
1+
#50000
0+
#55000
1+
#60000
0+
#65000
1+
#70000
0+
#75000
1+
#80000
0+
#85000
1+
#90000
0+
#95000
1+
#100000
0+
0-
#105000
1+
#110000
0+
#115000
1+
#120000
0+
#125000
b1 :
b1010101010111011110011001101110111101110111111110001000100100010 .
b1010101010111011110011001101110111101110111111110001000100100010 1
10
1+
#130000
0+
#135000
b10 :
b10101010101110111100110011011101 (
b10101010101110111100110011011101 7
b11101110111111110001000100100010 '
b11101110111111110001000100100010 8
b1100000010101000000000010000000111100000000000010000000100000001 .
b1100000010101000000000010000000111100000000000010000000100000001 1
1+
#140000
0+
#145000
b11 :
1)
b0 "
b0 ;
b0 !
b0 <
b10011010010000111111001000000000000000000000000000000000000 .
b10011010010000111111001000000000000000000000000000000000000 1
1+
#150000
0+
#155000
1$
b10011010010000111111001000000000000000000000000000000000000 &
b10011010010000111111001000000000000000000000000000000000000 9
b1101111010101101101111101110111111001010111111101011101010111110 .
b1101111010101101101111101110111111001010111111101011101010111110 1
1+
#160000
0+
#165000
b0 :
1%
b1000100010001001000100010001000110011001100110100010001000100 &
b1000100010001001000100010001000110011001100110100010001000100 9
0)
1$
1/
b1000100010001001000100010001000110011001100110100010001000100 .
b1000100010001001000100010001000110011001100110100010001000100 1
1+
#170000
0+
#175000
b1 :
0%
0$
0/
00
1+
